check_cmake/__init__.py
check_cmake/checks.py
check_cmake/colour.py
check_cmake/grid.py
check_cmake/main.py
check_cmake/paths.py
check_cmake/utils.py
check_cmake/version.py
check_cmake/version.txt
check_cmake-0.5.3.dist-info/licenses/LICENSE.txt
check_cmake-0.5.3.dist-info/METADATA
check_cmake-0.5.3.dist-info/WHEEL
check_cmake-0.5.3.dist-info/entry_points.txt
check_cmake-0.5.3.dist-info/top_level.txt
check_cmake-0.5.3.dist-info/zip-safe
check_cmake-0.5.3.dist-info/RECORD
