Metadata-Version: 2.4
Name: check_cmake
Version: 0.5.3
Summary: A simple linter for CMake.
Author-email: Mark Gillard <mark.gillard@outlook.com.au>
License: MIT
Project-URL: Source, https://github.com/marzer/check-cmake
Project-URL: Tracker, https://github.com/marzer/check-cmake/issues
Project-URL: Funding, https://github.com/sponsors/marzer
Keywords: c++,cmake
Classifier: Development Status :: 3 - Alpha
Classifier: License :: OSI Approved :: MIT License
Classifier: Programming Language :: C
Classifier: Programming Language :: C++
Classifier: Topic :: Software Development :: Code Generators
Classifier: Topic :: Software Development :: Compilers
Classifier: Topic :: Software Development :: Build Tools
Classifier: Topic :: Utilities
Requires-Python: >=3.8
License-File: LICENSE.txt
Requires-Dist: misk>=0.8.1
Requires-Dist: colorama
Dynamic: license-file
